{
    "call": {
        "id": "60e7d534-6d27-40a4-9d3a-385a648e5b28",
        "tenant_code": "miitel-test",
        "details": [
            {
                "id": "60e7d534-6d27-40a4-9d3a-385a648e5b28",
                "dial_starts_at": "2023-11-28T07:26:18+00:00",
                "dial_answered_at": "2023-11-28T07:26:23+00:00",
                "dial_ends_at": "2023-11-28T07:29:34+00:00",
                "queueing_starts_at": null,
                "queueing_answered_at": null,
                "queueing_ends_at": null,
                "call_type": "OUTGOING_CALL",
                "circuit_number": "05000000000",
                "circuit_name": "05000000000",
                "from_number": null,
                "to_number": "09000000000",
                "previous_id": null,
                "minutes": "【議題】\n不明\n\n【重要なポイント】\n- 参加者が3分間待つことに合意したこと\n\n【今後取るべき方針】\n不明",
                "participants": [
                    {
                        "id": "018c14d2-5a39-5312-315a-249e9e94526e",
                        "from_to": "FROM",
                        "name": "revcomm tarou",
                        "company_name": null,
                        "login_id": "test@example.com"
                    },
                    {
                        "id": "018c14d2-5a39-97a5-dcc4-d4f894078335",
                        "from_to": "TO",
                        "name": null,
                        "company_name": null,
                        "login_id": null
                    }
                ]
            }
        ]
    },
    "ip_restricted": true
}