{
    "call_data": [
        {
            "call_data_id": "test_id",
            "audio_file_type": "mp3",
            "event_type": "OUTGOING_CALL",
            "groupname": null,
            "queue_name": null,
            "call_starts_at": "2022-12-09T03:41:48+00:00",
            "call_answered_at": "2023-11-28T07:26:23+00:00",
            "call_ends_at": "2023-11-28T07:29:34+00:00",
            "circuit_number": "05011112222",
            "audio_channel_type": "STEREO",
            "participants": [
                {
                    "type": "FROM",
                    "stereo_lr": "left",
                    "miitel_user_id": "9b1d82f5-9845-4158-9c7b-75e7c235d8e7",
                    "number": "05011112222",
                    "name": "RevComm太郎"
                },
                {
                    "type": "TO",
                    "stereo_lr": "left",
                    "miitel_user_id": null,
                    "number": "05033334444",
                    "name": null
                }
            ]
        }
    ]
}